Parlo_PDLLC/__init__.py
Parlo_PDLLC/parlo.py
parlo-0.0.1.dist-info/METADATA
parlo-0.0.1.dist-info/WHEEL
parlo-0.0.1.dist-info/RECORD
