Metadata-Version: 2.1
Name: Parlo
Version: 0.0.1
Summary: Parlo's life
Author-email: Dial <sial@plurallydial.com>
Classifier: License :: OSI Approved :: MIT License
Classifier: Operating System :: OS Independent
Classifier: Programming Language :: Python :: 3
Requires-Python: >=3.7
